MANIFEST.in
README.txt
setup.py
cmsplugin_fb_agenda/__init__.py
cmsplugin_fb_agenda/cms_plugins.py
cmsplugin_fb_agenda/models.py
cmsplugin_fb_agenda/settings.py
cmsplugin_fb_agenda.egg-info/PKG-INFO
cmsplugin_fb_agenda.egg-info/SOURCES.txt
cmsplugin_fb_agenda.egg-info/dependency_links.txt
cmsplugin_fb_agenda.egg-info/entry_points.txt
cmsplugin_fb_agenda.egg-info/not-zip-safe
cmsplugin_fb_agenda.egg-info/requires.txt
cmsplugin_fb_agenda.egg-info/top_level.txt
cmsplugin_fb_agenda/migrations/0001_initial.py
cmsplugin_fb_agenda/migrations/0002_auto__add_field_fbagendaplugin_count.py
cmsplugin_fb_agenda/migrations/__init__.py
cmsplugin_fb_agenda/templates/cmsplugin_fb_agenda/agenda.html
docs/HISTORY.rst
docs/license.txt