Metadata-Version: 1.1
Name: cmsplugin-fb-agenda
Version: 0.2
Summary: django-cms plugin: display the agenda of a facebook user
Home-page: http://lagunak.gisa-elkartea.org/projects/cmplugin-fb-agenda
Author: GISA Elkartea
Author-email: kontaktua@gisa-elkartea.org
License: GPL
Platform: UNKNOWN
Classifier: Programming Language :: Python
Classifier: Topic :: Software Development :: Libraries :: Python Modules
